glif_client/__init__.py
glif_client/client.py
glif_client-0.1.2.dist-info/LICENSE
glif_client-0.1.2.dist-info/METADATA
glif_client-0.1.2.dist-info/WHEEL
glif_client-0.1.2.dist-info/top_level.txt
glif_client-0.1.2.dist-info/RECORD
