Metadata-Version: 2.1
Name: glif_client
Version: 0.1.2
Summary: A wrapper for the Glif API
Home-page: 
Author: Raphael Vorias
Author-email: raphael@glif.app
Classifier: Programming Language :: Python :: 3
Classifier: License :: OSI Approved :: MIT License
Classifier: Operating System :: OS Independent
Requires-Python: >=3.6
License-File: LICENSE
Requires-Dist: requests >=2.25.1
Requires-Dist: aiohttp >=3.7.4
